[
  {
    "FirstTwenty": [
      {
        "One": "FISTjan09",
        "Two": "jarkVICK1234",
        "Three": "@paul1234",
        "Four": "@OSca1234#",
        "Five": "@Ugo1234#",
        "Six": "@ObiMart123#",
        "Seven": "@Loda123#",
        "Eight": "pedpas12",
        "Nine": "#Gose1998",
        "Ten": "peterpask123"
      },
      {
        "One": "datnyto79",
        "Two": "rafel123#",
        "Three": "kelechi765",
        "Four": "joshphilip20",
        "Five": "komercy23",
        "Six": "gracelove789#",
        "Seven": "jameski90",
        "Eight": "Ada11345678",
        "Nine": "#pat5900",
        "Ten": "#0scapet123"
      },
      {
        "One": "#kolosjames12",
        "Two": "#JulietEst123",
        "Three": "*solomone123",
        "Four": "#blessing123",
        "Five": "appinessfabian13022021",
        "Six": "anddyfrank13022021",
        "Seven": "ashlyfried13022021",
        "Eight": "abobbyfriday13022021",
        "Nine": "ampadufed13022021",
        "Ten": "#johny31"
      },
      {
        "One": "#kings2021",
        "Two": "armoironflash13022021",
        "Three": "#prepen333",
        "Four": "#12345ugo",
        "Five": "#00000Code",
        "Six": "#12345mercy",
        "Seven": "#11111philip",
        "Eight": "#samC123",
        "Nine": "#goddy123",
        "Ten": "00000chikA"
      },
      {
        "One": "#ksochukwu120",
        "Two": "#samsone123",
        "Three": "#petpe098",
        "Four": "#klis2233",
        "Five": "loster123#",
        "Six": "pauluu100",
        "Seven": "andkin1m",
        "Eight": "martbiz1m",
        "Nine": "levi1234#",
        "Ten": "#prince123"
      },
      {
        "One": "Jams12345",
        "Two": "pau12345",
        "Three": "#salevi100",
        "Four": "#tomacheal1",
        "Five": "#dolas665",
        "Six": "#jojojo12345",
        "Seven": "mJeccus123",
        "Eight": "Book12345",
        "Nine": "Doors12345",
        "Ten": "#esterno123"
      },
      {
        "One": "#omega12345",
        "Two": "JANsixteen12",
        "Three": "JANseveteen2",
        "Four": "JANeighty12",
        "Five": "JANnineteen12"
      }
    ]
  }
]
